subscrape/__init__.py
subscrape/blockscout_wrapper.py
subscrape/moonscan_wrapper.py
subscrape/subscan_wrapper.py
subscrape/db/sectorized_storage_manager.py
subscrape/db/subscrape_db.py
subscrape/decode/decode_evm_log.py
subscrape/decode/decode_evm_transaction.py
subscrape/scrapers/__init__.py
subscrape/scrapers/moonbeam_scraper.py
subscrape/scrapers/parachain_scraper.py
subscrape/scrapers/scrape_config.py
subscrape-1.0.1rc1.dist-info/METADATA
subscrape-1.0.1rc1.dist-info/WHEEL
subscrape-1.0.1rc1.dist-info/licenses/AUTHORS
subscrape-1.0.1rc1.dist-info/licenses/LICENSE
subscrape-1.0.1rc1.dist-info/RECORD
