Metadata-Version: 2.1
Name: subscrape
Version: 1.0.1rc1
Summary: A Python scraper for substrate chains
Project-URL: Homepage, https://github.com/ChaosDAO-org/subscrape
Project-URL: Bug Tracker, https://github.com/ChaosDAO-org/subscrape/issues
Author-email: Tommi Enenkel <tommi.enenkel@gmail.com>, spaz <spazcoin@gmail.com>
License: MIT License
Classifier: License :: OSI Approved :: MIT License
Classifier: Operating System :: OS Independent
Classifier: Programming Language :: Python :: 3
Requires-Python: >=3.7
Requires-Dist: eth-utils
Requires-Dist: hexbytes
Requires-Dist: httpx[http2]
Requires-Dist: pandas
Requires-Dist: ratelimit
Requires-Dist: simplejson
Requires-Dist: substrate-interface
Requires-Dist: web3>5.0
